onceuponai-0.0.2.dist-info/METADATA
onceuponai-0.0.2.dist-info/WHEEL
onceuponai-0.0.2.dist-info/license_files/LICENSE
onceuponai/__init__.py
onceuponai/onceuponai.abi3.so
onceuponai-0.0.2.dist-info/RECORD
